rpo/__init__.py
rpo/analyzer.py
rpo/db.py
rpo/exceptions.py
rpo/main.py
rpo/models.py
rpo/plotting.py
rpo/server.py
rpo/types.py
rpo-0.1.0a10.dist-info/METADATA
rpo-0.1.0a10.dist-info/WHEEL
rpo-0.1.0a10.dist-info/entry_points.txt
rpo-0.1.0a10.dist-info/licenses/LICENSE
rpo-0.1.0a10.dist-info/RECORD
