Metadata-Version: 2.4
Name: rpo
Version: 0.1.0a10
Summary: Repository Participation Observer. A tool for investigation git repository contribution data and patterns.
Project-URL: Homepage, https://github.com/crlane/rpo
Project-URL: Documentation, https://rpo.readthedocs.io/en/latest/
Project-URL: Repsoitory, https://github.com/crlane/rpo
Project-URL: Bug Tracker, https://github.com/crlane/rpo/issues
Project-URL: Changelog, https://github.com/crlane/rpo/blob/master/CHANGELOG.md
Author-email: Cameron Lane <crlane@adamanteus.com>
Maintainer-email: Cameron Lane <crlane@adamanteus.com>
License-Expression: MIT
License-File: LICENSE
Keywords: git,repository,statistics
Classifier: Development Status :: 3 - Alpha
Classifier: License :: OSI Approved :: MIT License
Requires-Python: >=3.13
Requires-Dist: altair[all]>=5.5.0
Requires-Dist: click-aliases>=1.0.5
Requires-Dist: click>=8.2.1
Requires-Dist: duckdb>=1.3.1
Requires-Dist: gitpython>=3.1.44
Requires-Dist: polars[pyarrow]>=1.30.0
Requires-Dist: pydanclick>=0.5.1
Requires-Dist: pydantic>=2.11.5
